setup.py
meteogram_py.egg-info/PKG-INFO
meteogram_py.egg-info/SOURCES.txt
meteogram_py.egg-info/dependency_links.txt
meteogram_py.egg-info/not-zip-safe
meteogram_py.egg-info/top_level.txt
meteogrampy/__init__.py
meteogrampy/styles.py