Metadata-Version: 1.1
Name: meteogram-py
Version: 0.0.1
Summary: Python module built around Matplotlib for quickly creating meteograms from weather data.
Home-page: UNKNOWN
Author: Weather Decision Technologies
Author-email: pkamis@wdtinc.com
License: UNKNOWN
Platform: UNKNOWN
Classifier: Development Status :: 3 - Alpha
Classifier: Intended Audience :: Developers
Classifier: Natural Language :: English
Classifier: Programming Language :: Python
Classifier: Programming Language :: Python :: 2.7
